setup.py
windutil/__init__.py
windutil/argparser.py
windutil/main.py
windutil/scrlogger.py
windutil.egg-info/PKG-INFO
windutil.egg-info/SOURCES.txt
windutil.egg-info/dependency_links.txt
windutil.egg-info/entry_points.txt
windutil.egg-info/top_level.txt