Metadata-Version: 1.1
Name: windutil
Version: 1.0.6
Summary: A command-line utility to manage the docker containers of the Wind application.
Home-page: https://github.com/amaret/wind.util
Author: Amaret, Inc
Author-email: develop@amaret.com
License: APACHE2
Keywords: python docker
Platform: UNKNOWN
Classifier: Development Status :: 5 - Production/Stable
Classifier: Intended Audience :: Developers
Classifier: Natural Language :: English
Classifier: License :: OSI Approved :: GNU General Public License v2 (GPLv2)
Classifier: Topic :: Software Development :: Compilers
Classifier: Operating System :: OS Independent
Classifier: Programming Language :: Python
Classifier: Programming Language :: Python :: 2
Classifier: Programming Language :: Python :: 2.7
